{
    "bins": [
        20.2,
        40.4,
        60.6,
        80.9,
        101.1,
        121.3,
        141.5,
        161.7,
        181.9,
        202.2,
        222.4,
        242.6,
        262.8,
        283.0,
        303.2,
        323.5,
        343.7,
        363.9,
        384.1,
        404.3,
        424.5,
        444.8,
        465.0,
        485.2,
        505.4
    ],
    "experimental": [
        164.2,
        345.0,
        432.5,
        578.1,
        672.6,
        769.4,
        818.5,
        890.6,
        975.5,
        1116.2,
        1117.8,
        1198.9,
        1323.4,
        1398.8,
        1416.0,
        1507.3,
        1542.3,
        1491.0,
        1452.7,
        1447.4,
        1486.3,
        1446.8,
        1491.7,
        1531.5,
        1519.9
    ],
    "modelX": [
        0.0,
        5.1,
        10.2,
        15.3,
        20.4,
        25.5,
        30.6,
        35.7,
        40.8,
        45.9,
        51.1,
        56.2,
        61.3,
        66.4,
        71.5,
        76.6,
        81.7,
        86.8,
        91.9,
        97.0,
        102.1,
        107.2,
        112.3,
        117.4,
        122.5,
        127.6,
        132.7,
        137.8,
        142.9,
        148.0,
        153.2,
        158.3,
        163.4,
        168.5,
        173.6,
        178.7,
        183.8,
        188.9,
        194.0,
        199.1,
        204.2,
        209.3,
        214.4,
        219.5,
        224.6,
        229.7,
        234.8,
        239.9,
        245.0,
        250.1,
        255.3,
        260.4,
        265.5,
        270.6,
        275.7,
        280.8,
        285.9,
        291.0,
        296.1,
        301.2,
        306.3,
        311.4,
        316.5,
        321.6,
        326.7,
        331.8,
        336.9,
        342.0,
        347.1,
        352.3,
        357.4,
        362.5,
        367.6,
        372.7,
        377.8,
        382.9,
        388.0,
        393.1,
        398.2,
        403.3,
        408.4,
        413.5,
        418.6,
        423.7,
        428.8,
        433.9,
        439.0,
        444.1,
        449.2,
        454.4,
        459.5,
        464.6,
        469.7,
        474.8,
        479.9,
        485.0,
        490.1,
        495.2,
        500.3,
        505.4
    ],
    "modelGauss": [
        0.0,
        1.6,
        6.4,
        14.3,
        25.3,
        39.3,
        56.2,
        76.0,
        98.5,
        123.5,
        150.9,
        180.5,
        212.2,
        245.8,
        281.1,
        317.8,
        355.8,
        394.8,
        434.7,
        475.3,
        516.3,
        557.6,
        599.0,
        640.2,
        681.2,
        721.8,
        761.7,
        801.0,
        839.4,
        876.8,
        913.2,
        948.4,
        982.5,
        1015.2,
        1046.6,
        1076.6,
        1105.2,
        1132.4,
        1158.2,
        1182.6,
        1205.5,
        1227.1,
        1247.3,
        1266.2,
        1283.8,
        1300.2,
        1315.3,
        1329.4,
        1342.3,
        1354.2,
        1365.1,
        1375.1,
        1384.2,
        1392.4,
        1400.0,
        1406.8,
        1412.9,
        1418.5,
        1423.5,
        1427.9,
        1431.9,
        1435.5,
        1438.7,
        1441.5,
        1444.0,
        1446.2,
        1448.1,
        1449.8,
        1451.3,
        1452.6,
        1453.8,
        1454.8,
        1455.6,
        1456.4,
        1457.0,
        1457.6,
        1458.1,
        1458.5,
        1458.8,
        1459.1,
        1459.4,
        1459.6,
        1459.8,
        1460.0,
        1460.1,
        1460.2,
        1460.3,
        1460.4,
        1460.4,
        1460.5,
        1460.5,
        1460.6,
        1460.6,
        1460.6,
        1460.7,
        1460.7,
        1460.7,
        1460.7,
        1460.7,
        1460.7
    ],
    "modelExp": [
        0.0,
        49.8,
        98.0,
        144.6,
        189.7,
        233.4,
        275.7,
        316.6,
        356.1,
        394.4,
        431.5,
        467.4,
        502.1,
        535.7,
        568.2,
        599.6,
        630.1,
        659.5,
        688.0,
        715.6,
        742.3,
        768.1,
        793.1,
        817.3,
        840.7,
        863.4,
        885.3,
        906.5,
        927.0,
        946.9,
        966.1,
        984.7,
        1002.7,
        1020.2,
        1037.0,
        1053.3,
        1069.1,
        1084.4,
        1099.2,
        1113.5,
        1127.3,
        1140.7,
        1153.7,
        1166.2,
        1178.4,
        1190.1,
        1201.5,
        1212.5,
        1223.2,
        1233.5,
        1243.4,
        1253.1,
        1262.4,
        1271.5,
        1280.2,
        1288.7,
        1296.9,
        1304.8,
        1312.5,
        1319.9,
        1327.1,
        1334.0,
        1340.7,
        1347.3,
        1353.6,
        1359.6,
        1365.5,
        1371.3,
        1376.8,
        1382.1,
        1387.3,
        1392.3,
        1397.1,
        1401.8,
        1406.4,
        1410.8,
        1415.0,
        1419.1,
        1423.1,
        1426.9,
        1430.7,
        1434.3,
        1437.8,
        1441.1,
        1444.4,
        1447.6,
        1450.6,
        1453.6,
        1456.5,
        1459.2,
        1461.9,
        1464.5,
        1467.0,
        1469.5,
        1471.8,
        1474.1,
        1476.3,
        1478.4,
        1480.5,
        1482.5
    ],
    "modelSph": [
        0.0,
        31.3,
        62.7,
        94.0,
        125.2,
        156.4,
        187.6,
        218.7,
        249.6,
        280.5,
        311.3,
        342.0,
        372.5,
        402.9,
        433.1,
        463.1,
        493.0,
        522.6,
        552.1,
        581.3,
        610.3,
        639.0,
        667.5,
        695.7,
        723.6,
        751.2,
        778.6,
        805.6,
        832.2,
        858.5,
        884.5,
        910.1,
        935.3,
        960.1,
        984.5,
        1008.5,
        1032.0,
        1055.2,
        1077.8,
        1100.0,
        1121.7,
        1142.9,
        1163.6,
        1183.8,
        1203.4,
        1222.5,
        1241.0,
        1259.0,
        1276.4,
        1293.2,
        1309.4,
        1325.0,
        1340.0,
        1354.3,
        1367.9,
        1380.9,
        1393.2,
        1404.8,
        1415.7,
        1425.9,
        1435.4,
        1444.1,
        1452.1,
        1459.3,
        1465.7,
        1471.3,
        1476.2,
        1480.2,
        1483.4,
        1485.7,
        1487.2,
        1487.8,
        1487.9,
        1487.9,
        1487.9,
        1487.9,
        1487.9,
        1487.9,
        1487.9,
        1487.9,
        1487.9,
        1487.9,
        1487.9,
        1487.9,
        1487.9,
        1487.9,
        1487.9,
        1487.9,
        1487.9,
        1487.9,
        1487.9,
        1487.9,
        1487.9,
        1487.9,
        1487.9,
        1487.9,
        1487.9,
        1487.9,
        1487.9,
        1487.9
    ],
    "paramsGauss": [
        309.21491396991917,
        1460.7548033728267,
        0
    ],
    "paramsExp": [
        466.65883773025655,
        1542.3434061676737,
        0
    ],
    "paramsSph": [
        363.58217431785044,
        1487.8649757476771,
        0
    ]
}